beetle_preview/__init__.py
Beetle_Preview-0.1.0.dist-info/WHEEL
Beetle_Preview-0.1.0.dist-info/DESCRIPTION.rst
Beetle_Preview-0.1.0.dist-info/RECORD
Beetle_Preview-0.1.0.dist-info/METADATA
Beetle_Preview-0.1.0.dist-info/metadata.json
Beetle_Preview-0.1.0.dist-info/top_level.txt
