Metadata-Version: 2.0
Name: Beetle-Preview
Version: 0.1.0
Summary: Local test server plugin for Beetle
Home-page: https://github.com/cknv/beetle-preview
Author: Esben Sonne
Author-email: esbensonne+code@gmail.com
License: MIT
Platform: UNKNOWN
Classifier: Environment :: Plugins
Classifier: Environment :: Console
Classifier: Development Status :: 3 - Alpha
Classifier: Intended Audience :: Developers
Classifier: License :: OSI Approved :: MIT License
Classifier: Programming Language :: Python :: 3
Classifier: Topic :: Internet :: WWW/HTTP :: HTTP Servers
Requires-Dist: watchdog
